spacecraft_thermal_multi_node_analysis/__init__.py
spacecraft_thermal_multi_node_analysis/batch_analysis.py
spacecraft_thermal_multi_node_analysis/compare_temperature_data.py
spacecraft_thermal_multi_node_analysis/multi_node_analysis.py
spacecraft_thermal_multi_node_analysis/py.typed
spacecraft_thermal_multi_node_analysis/utils/__init__.py
spacecraft_thermal_multi_node_analysis/utils/config_loader.py
spacecraft_thermal_multi_node_analysis/utils/dataclasses.py
spacecraft_thermal_multi_node_analysis/utils/orbit_utils.py
spacecraft_thermal_multi_node_analysis/utils/plotting_utils.py
spacecraft_thermal_multi_node_analysis/utils/satellite_config.py
spacecraft_thermal_multi_node_analysis/utils/thermal_utils.py
spacecraft_thermal_multi_node_analysis-0.1.0.dist-info/licenses/LICENSE
spacecraft_thermal_multi_node_analysis-0.1.0.dist-info/WHEEL
spacecraft_thermal_multi_node_analysis-0.1.0.dist-info/entry_points.txt
spacecraft_thermal_multi_node_analysis-0.1.0.dist-info/METADATA
spacecraft_thermal_multi_node_analysis-0.1.0.dist-info/RECORD
