Metadata-Version: 2.4
Name: spacecraft-thermal-multi-node-analysis
Version: 0.1.0
Summary: 衛星の多節点熱解析プログラム
License-Expression: MIT
License-File: LICENSE
Classifier: License :: OSI Approved :: MIT License
Classifier: Programming Language :: Python
Classifier: Programming Language :: Python :: 3 :: Only
Classifier: Programming Language :: Python :: 3.12
Classifier: Programming Language :: Python :: 3.13
Classifier: Programming Language :: Python :: 3.14
Classifier: Typing :: Typed
Requires-Dist: matplotlib>=3.4.0
Requires-Dist: numpy>=1.21.0
Requires-Dist: pandas>=1.3.0
Requires-Dist: pyyaml>=5.4.0
Requires-Dist: rich>=14.2.0
Requires-Python: >=3.12
Project-URL: Issues, https://github.com/ut-issl/spacecraft-thermal-multi-node-analysis/issues
Project-URL: Repository, https://github.com/ut-issl/spacecraft-thermal-multi-node-analysis
